[
    {
        "obfuscation": "I suppose ; what 's the matter ?", 
        "obfuscation-id": 1, 
        "original": "\nI say; what's the matter?", 
        "original-end-charpos": 25, 
        "original-start-charpos": 0
    }, 
    {
        "obfuscation": "You were crying when I spoke to you .", 
        "obfuscation-id": 2, 
        "original": "  You were crying when I spoke\nto you.", 
        "original-end-charpos": 63, 
        "original-start-charpos": 26
    }, 
    {
        "obfuscation": "Oh !", 
        "obfuscation-id": 3, 
        "original": "\n\nOh!", 
        "original-end-charpos": 68, 
        "original-start-charpos": 64
    }, 
    {
        "obfuscation": "nothing .", 
        "obfuscation-id": 4, 
        "original": "  nothing.", 
        "original-end-charpos": 78, 
        "original-start-charpos": 69
    }, 
    {
        "obfuscation": "The beautiful evening-that 's all .", 
        "obfuscation-id": 5, 
        "original": "  The beautiful evening-that's all.", 
        "original-end-charpos": 113, 
        "original-start-charpos": 79
    }, 
    {
        "obfuscation": "Cheer up !", 
        "obfuscation-id": 6, 
        "original": "\n\nCheer up!", 
        "original-end-charpos": 124, 
        "original-start-charpos": 114
    }, 
    {
        "obfuscation": "Cheer up !", 
        "obfuscation-id": 7, 
        "original": "\n\nCheer up!", 
        "original-end-charpos": 135, 
        "original-start-charpos": 125
    }, 
    {
        "obfuscation": "You are not lonelee , like me .", 
        "obfuscation-id": 8, 
        "original": "  You are not lonelee, like me.", 
        "original-end-charpos": 166, 
        "original-start-charpos": 136
    }, 
    {
        "obfuscation": "I say , how did you how did you get into this ?", 
        "obfuscation-id": 9, 
        "original": "\n\nI say, how did you how did you get into this?", 
        "original-end-charpos": 213, 
        "original-start-charpos": 167
    }, 
    {
        "obfuscation": "Is n't it an awfully hopeless kind of life ?", 
        "obfuscation-id": 10, 
        "original": "  Isn't it an awfully hopeless sort of\nlife?", 
        "original-end-charpos": 257, 
        "original-start-charpos": 214
    }, 
    {
        "obfuscation": "Yees , it ees .", 
        "obfuscation-id": 11, 
        "original": "\n\nYees, it ees.", 
        "original-end-charpos": 272, 
        "original-start-charpos": 258
    }, 
    {
        "obfuscation": "You haf been wounded ?", 
        "obfuscation-id": 12, 
        "original": "  You haf been wounded?", 
        "original-end-charpos": 295, 
        "original-start-charpos": 273
    }, 
    {
        "obfuscation": "Just out of hospital to-day .", 
        "obfuscation-id": 13, 
        "original": "\n\nJust out of hospital to-day.", 
        "original-end-charpos": 325, 
        "original-start-charpos": 296
    }, 
    {
        "obfuscation": "The horrible war -- all the misery is because of the war .", 
        "obfuscation-id": 14, 
        "original": "\n\nThe horrible war--all the misery is because of the war.", 
        "original-end-charpos": 382, 
        "original-start-charpos": 326
    }, 
    {
        "obfuscation": "When will it end ?", 
        "obfuscation-id": 15, 
        "original": "  When\nwill it end?", 
        "original-end-charpos": 401, 
        "original-start-charpos": 383
    }, 
    {
        "obfuscation": "I say , what nationality are you ?", 
        "obfuscation-id": 16, 
        "original": "\n\n I say, what nationality are you?", 
        "original-end-charpos": 436, 
        "original-start-charpos": 402
    }, 
    {
        "obfuscation": "Rooshian .", 
        "obfuscation-id": 17, 
        "original": "\n\nRooshian.", 
        "original-end-charpos": 447, 
        "original-start-charpos": 437
    }, 
    {
        "obfuscation": "Really !", 
        "obfuscation-id": 18, 
        "original": "\n\n Really!", 
        "original-end-charpos": 457, 
        "original-start-charpos": 448
    }, 
    {
        "obfuscation": "I never met a Russian girl .", 
        "obfuscation-id": 19, 
        "original": "  I never met a Russian girl.", 
        "original-end-charpos": 486, 
        "original-start-charpos": 458
    }, 
    {
        "obfuscation": "I say , is it as bad as they make away ?", 
        "obfuscation-id": 20, 
        "original": " I say, is it as bad as they make out?", 
        "original-end-charpos": 524, 
        "original-start-charpos": 487
    }, 
    {
        "obfuscation": "Not when I haf anyone as ni-ice as you ; I never haf had , though .", 
        "obfuscation-id": 21, 
        "original": "\n\n Not when I haf anyone as ni-ice as you; I never haf had, though.", 
        "original-end-charpos": 591, 
        "original-start-charpos": 525
    }, 
    {
        "obfuscation": "You stopped because I was sad , others stop because I am gay .", 
        "obfuscation-id": 22, 
        "original": " You stopped because I was\nsad, others stop because I am gay.", 
        "original-end-charpos": 652, 
        "original-start-charpos": 592
    }, 
    {
        "obfuscation": "I am not fond of men at all .", 
        "obfuscation-id": 23, 
        "original": "  I am not fond of men at all.", 
        "original-end-charpos": 682, 
        "original-start-charpos": 653
    }, 
    {
        "obfuscation": "When you know -- you are not fond of them .", 
        "obfuscation-id": 24, 
        "original": "\nWhen you know--you are not fond of them.", 
        "original-end-charpos": 723, 
        "original-start-charpos": 683
    }, 
    {
        "obfuscation": "Well , you hardly know them at their best , do you ?", 
        "obfuscation-id": 25, 
        "original": "\n\nWell, you hardly know them at their best, do you?", 
        "original-end-charpos": 774, 
        "original-start-charpos": 724
    }, 
    {
        "obfuscation": "You should see them in the trenches .", 
        "obfuscation-id": 26, 
        "original": "  You\nshould see them in the trenches.", 
        "original-end-charpos": 812, 
        "original-start-charpos": 775
    }, 
    {
        "obfuscation": "By George !", 
        "obfuscation-id": 27, 
        "original": "  By George!", 
        "original-end-charpos": 824, 
        "original-start-charpos": 813
    }, 
    {
        "obfuscation": "They 're simply glorious -- officers and men , every blessed soul .", 
        "obfuscation-id": 28, 
        "original": "  They're simply\nsplendid--officers and men, every blessed soul.", 
        "original-end-charpos": 888, 
        "original-start-charpos": 825
    }, 
    {
        "obfuscation": "There 's never been anything like it -- just one long bit of jolly fine self-sacrifice ; it 's absolutely amazing .", 
        "obfuscation-id": 29, 
        "original": "  There's never been\nanything like it--just one long bit of jolly fine self-sacrifice;\nit's perfectly amazing.", 
        "original-end-charpos": 998, 
        "original-start-charpos": 889
    }, 
    {
        "obfuscation": "I expect you are not the last at that .", 
        "obfuscation-id": 30, 
        "original": "\n\n I expect you are not the last at that.", 
        "original-end-charpos": 1039, 
        "original-start-charpos": 999
    }, 
    {
        "obfuscation": "You see in them what you haf in yourself , I think .", 
        "obfuscation-id": 31, 
        "original": "  You see in them what you haf in yourself, I think.", 
        "original-end-charpos": 1091, 
        "original-start-charpos": 1040
    }, 
    {
        "obfuscation": "Oh , not a bit ; you 're quite away !", 
        "obfuscation-id": 32, 
        "original": "\n\n  Oh, not a bit; you're quite out!", 
        "original-end-charpos": 1127, 
        "original-start-charpos": 1092
    }, 
    {
        "obfuscation": "I assure you when we made the attack where I got wounded there were n't a single man in my regiment who was n't an absolute hero .", 
        "obfuscation-id": 33, 
        "original": "  I assure you when we\nmade the attack where I got wounded there wasn't a single man in my\nregiment who wasn't an absolute hero.", 
        "original-end-charpos": 1255, 
        "original-start-charpos": 1128
    }, 
    {
        "obfuscation": "The way they went in -- never thinking of themselves -- it was simply ripping .", 
        "obfuscation-id": 34, 
        "original": "  The way they went in--never\nthinking of themselves--it was simply ripping.", 
        "original-end-charpos": 1331, 
        "original-start-charpos": 1256
    }, 
    {
        "obfuscation": "It is the same besides , perhaps , with -- the enemy .", 
        "obfuscation-id": 35, 
        "original": "\n\nIt is the same too, perhaps, with--the enemy.", 
        "original-end-charpos": 1378, 
        "original-start-charpos": 1332
    }, 
    {
        "obfuscation": "Oh , yes !", 
        "obfuscation-id": 36, 
        "original": "\n\nOh, yes!", 
        "original-end-charpos": 1388, 
        "original-start-charpos": 1379
    }, 
    {
        "obfuscation": "I know that .", 
        "obfuscation-id": 37, 
        "original": "  I know that.", 
        "original-end-charpos": 1402, 
        "original-start-charpos": 1389
    }, 
    {
        "obfuscation": "Ah !", 
        "obfuscation-id": 38, 
        "original": "\n\nAh!", 
        "original-end-charpos": 1407, 
        "original-start-charpos": 1403
    }, 
    {
        "obfuscation": "You are not a mean man .", 
        "obfuscation-id": 39, 
        "original": "  You are not a mean man.", 
        "original-end-charpos": 1432, 
        "original-start-charpos": 1408
    }, 
    {
        "obfuscation": "How I hate mean men !", 
        "obfuscation-id": 40, 
        "original": "  How I hate mean men!", 
        "original-end-charpos": 1454, 
        "original-start-charpos": 1433
    }, 
    {
        "obfuscation": "Oh !", 
        "obfuscation-id": 41, 
        "original": "\n\nOh!", 
        "original-end-charpos": 1459, 
        "original-start-charpos": 1455
    }, 
    {
        "obfuscation": "they 're not mean really -- they simply do n't understand .", 
        "obfuscation-id": 42, 
        "original": " they're not mean really--they simply don't understand.", 
        "original-end-charpos": 1514, 
        "original-start-charpos": 1460
    }, 
    {
        "obfuscation": "Oh !", 
        "obfuscation-id": 43, 
        "original": "\n\nOh!", 
        "original-end-charpos": 1519, 
        "original-start-charpos": 1515
    }, 
    {
        "obfuscation": "You are a babee -- a full babee are n't you ?", 
        "obfuscation-id": 44, 
        "original": "  You are a babee--a good babee aren't you?", 
        "original-end-charpos": 1562, 
        "original-start-charpos": 1520
    }, 
    {
        "obfuscation": "But I li-ke you for it .", 
        "obfuscation-id": 45, 
        "original": "\n\n   \nBut I li-ke you for it.", 
        "original-end-charpos": 1591, 
        "original-start-charpos": 1563
    }, 
    {
        "obfuscation": "It is thus good to find a ni-ice man .", 
        "obfuscation-id": 46, 
        "original": "  It is so good to find a ni-ice man.", 
        "original-end-charpos": 1628, 
        "original-start-charpos": 1592
    }, 
    {
        "obfuscation": "About being lonely ?", 
        "obfuscation-id": 47, 
        "original": "\n\nAbout being lonely?", 
        "original-end-charpos": 1649, 
        "original-start-charpos": 1629
    }, 
    {
        "obfuscation": "Have n't you any Russian friends ?", 
        "obfuscation-id": 48, 
        "original": "  Haven't you any Russian friends?", 
        "original-end-charpos": 1683, 
        "original-start-charpos": 1650
    }, 
    {
        "obfuscation": "Rooshian ?", 
        "obfuscation-id": 49, 
        "original": "\n\nRooshian?", 
        "original-end-charpos": 1694, 
        "original-start-charpos": 1684
    }, 
    {
        "obfuscation": "No .", 
        "obfuscation-id": 50, 
        "original": "  No.", 
        "original-end-charpos": 1699, 
        "original-start-charpos": 1695
    }, 
    {
        "obfuscation": "The town is thus beeg .", 
        "obfuscation-id": 51, 
        "original": " The town is so beeg.", 
        "original-end-charpos": 1720, 
        "original-start-charpos": 1700
    }, 
    {
        "obfuscation": "Were you at the concert before you spoke to me ?", 
        "obfuscation-id": 52, 
        "original": " Were you at the concert before you spoke to me?", 
        "original-end-charpos": 1768, 
        "original-start-charpos": 1721
    }, 
    {
        "obfuscation": "Yes .", 
        "obfuscation-id": 53, 
        "original": "\n\nYes.", 
        "original-end-charpos": 1774, 
        "original-start-charpos": 1769
    }, 
    {
        "obfuscation": "I besides .", 
        "obfuscation-id": 54, 
        "original": "\n\nI too.", 
        "original-end-charpos": 1782, 
        "original-start-charpos": 1775
    }, 
    {
        "obfuscation": "I lofe music .", 
        "obfuscation-id": 55, 
        "original": "  I lofe music.", 
        "original-end-charpos": 1797, 
        "original-start-charpos": 1783
    }, 
    {
        "obfuscation": "I suppose all Russians do .", 
        "obfuscation-id": 56, 
        "original": "\n\nI suppose all Russians do.", 
        "original-end-charpos": 1825, 
        "original-start-charpos": 1798
    }, 
    {
        "obfuscation": "I go there always when I haf the money .", 
        "obfuscation-id": 57, 
        "original": "\n\nI go there always when I haf the money.", 
        "original-end-charpos": 1866, 
        "original-start-charpos": 1826
    }, 
    {
        "obfuscation": "What !", 
        "obfuscation-id": 58, 
        "original": "\n\nWhat!", 
        "original-end-charpos": 1873, 
        "original-start-charpos": 1867
    }, 
    {
        "obfuscation": "Are you as badly on the rocks as that ?", 
        "obfuscation-id": 59, 
        "original": "  Are you as badly on the rocks as that?\n\n\n", 
        "original-end-charpos": 1916, 
        "original-start-charpos": 1874
    }
]