[
    {
        "obfuscation": "\ufeff TV-the nanny of the 21th century Since it 's entry into our homes in the mid 20th century the TV 's role in our lives has grown .", 
        "obfuscation-id": 1, 
        "original": "\ufeff TV-the nanny of the 21th century  Since it's entry into our homes in the mid 20th century the TV's role in our lives has grown.", 
        "original-end-charpos": 128, 
        "original-start-charpos": 0
    }, 
    {
        "obfuscation": "Today it is the role model for many young people , who watch the world mainly via the screen .", 
        "obfuscation-id": 2, 
        "original": " \nToday it is the role model for many young people, who watch the world mainly via the screen.", 
        "original-end-charpos": 222, 
        "original-start-charpos": 129
    }, 
    {
        "obfuscation": "The TV , instead of parents , has become the one to tell us what is significant , how to act and what to look like .", 
        "obfuscation-id": 3, 
        "original": " \nThe TV, instead of parents, has become the one to tell us what is important, how to act and what to look like.", 
        "original-end-charpos": 334, 
        "original-start-charpos": 223
    }, 
    {
        "obfuscation": "As a result kids are getting fatter from lack of exercise , while anorexia is spreading .", 
        "obfuscation-id": 4, 
        "original": " \nAs a result kids are getting fatter from lack of exercise, while anorexia is spreading.", 
        "original-end-charpos": 423, 
        "original-start-charpos": 335
    }, 
    {
        "obfuscation": "Children are getting killed by other children .", 
        "obfuscation-id": 5, 
        "original": " \nChildren are getting killed by other children.", 
        "original-end-charpos": 471, 
        "original-start-charpos": 424
    }, 
    {
        "obfuscation": "How can it be that such a great instrument for learning and understanding has become our large enemy ?", 
        "obfuscation-id": 6, 
        "original": " \nHow can it be that such a great instrument for learning and understanding has become our biggest enemy?", 
        "original-end-charpos": 576, 
        "original-start-charpos": 472
    }, 
    {
        "obfuscation": "any kids learn from a very young age to deal with the TV at home .", 
        "obfuscation-id": 7, 
        "original": " \nany kids learn from a very young age to deal with the TV at home.", 
        "original-end-charpos": 643, 
        "original-start-charpos": 577
    }, 
    {
        "obfuscation": "They know how to handle the remote even before they 've stopped using diapers .", 
        "obfuscation-id": 8, 
        "original": " \nThey know how to handle the remote even before they've stopped using diapers.", 
        "original-end-charpos": 722, 
        "original-start-charpos": 644
    }, 
    {
        "obfuscation": "After a couple of years Nintendo and Playstation takes place under the TV , alongside with the video or DVD-player .", 
        "obfuscation-id": 9, 
        "original": " \nAfter a couple of years Nintendo and Playstation takes place under the TV, alongside with the video or DVD-player.", 
        "original-end-charpos": 838, 
        "original-start-charpos": 723
    }, 
    {
        "obfuscation": "Why do parents allow their children to spend thus much time with television ?", 
        "obfuscation-id": 10, 
        "original": " \nWhy do parents allow their children to spend so much time with television?", 
        "original-end-charpos": 914, 
        "original-start-charpos": 839
    }, 
    {
        "obfuscation": "The answer is quite comfortable .", 
        "obfuscation-id": 11, 
        "original": " \nThe answer is quite easy.", 
        "original-end-charpos": 941, 
        "original-start-charpos": 915
    }, 
    {
        "obfuscation": "Kids who watch television make n't run around and make a lot of noise and mess .", 
        "obfuscation-id": 12, 
        "original": " \nKids who watch television don't run around and make a lot of noise and mess.", 
        "original-end-charpos": 1019, 
        "original-start-charpos": 942
    }, 
    {
        "obfuscation": "The TV has become a nanny .", 
        "obfuscation-id": 13, 
        "original": " \nThe TV has become a nanny.", 
        "original-end-charpos": 1047, 
        "original-start-charpos": 1020
    }, 
    {
        "obfuscation": "The parents can do whatever they want to make while the kids watch TV or play videogames .", 
        "obfuscation-id": 14, 
        "original": " \nThe parents can do whatever they want to do while the kids watch TV or play videogames.", 
        "original-end-charpos": 1136, 
        "original-start-charpos": 1048
    }, 
    {
        "obfuscation": "I recently went to a party a friend was having .", 
        "obfuscation-id": 15, 
        "original": " \nI recently went to a party a friend was having.", 
        "original-end-charpos": 1185, 
        "original-start-charpos": 1137
    }, 
    {
        "obfuscation": "One of the guests had to bring her children along because she had no babysitter .", 
        "obfuscation-id": 16, 
        "original": " \nOne of the guests had to bring her children along because she had no babysitter.", 
        "original-end-charpos": 1267, 
        "original-start-charpos": 1186
    }, 
    {
        "obfuscation": "To solve the problem she brought a video tape the children could watch so they would n't exist in the way .", 
        "obfuscation-id": 17, 
        "original": " \nTo solve the problem she brought a video tape the children could watch so they wouldn't be in the way.", 
        "original-end-charpos": 1371, 
        "original-start-charpos": 1268
    }, 
    {
        "obfuscation": "It may sound as if parents nowadays make n't want to be together with their children .", 
        "obfuscation-id": 18, 
        "original": "  \t\nIt may sound as if parents nowadays don't want to be together with their children.", 
        "original-end-charpos": 1457, 
        "original-start-charpos": 1372
    }, 
    {
        "obfuscation": "This is of course not true .", 
        "obfuscation-id": 19, 
        "original": " \nThis is of course not true.", 
        "original-end-charpos": 1486, 
        "original-start-charpos": 1458
    }, 
    {
        "obfuscation": "The economy of a family much demands that both parents work full time .", 
        "obfuscation-id": 20, 
        "original": " \nThe economy of a family often demands that both parents work full time.", 
        "original-end-charpos": 1559, 
        "original-start-charpos": 1487
    }, 
    {
        "obfuscation": "After work there is cleaning , cooking , washing and more that have to be done at home .", 
        "obfuscation-id": 21, 
        "original": " \nAfter work there is cleaning, cooking, washing and more that have to be done at home.", 
        "original-end-charpos": 1646, 
        "original-start-charpos": 1560
    }, 
    {
        "obfuscation": "Spending time with children becomes a low priority chore and family business has to wait until weekends .", 
        "obfuscation-id": 22, 
        "original": " \nSpending time with children becomes a low priority chore and family business has to wait until weekends.", 
        "original-end-charpos": 1752, 
        "original-start-charpos": 1647
    }, 
    {
        "obfuscation": "The question is does it really matter that kids watch a lot of TV ?", 
        "obfuscation-id": 23, 
        "original": " \nThe question is does it really matter that kids watch a lot of TV?", 
        "original-end-charpos": 1820, 
        "original-start-charpos": 1753
    }, 
    {
        "obfuscation": "In America this question has been raised after a couple of serious crimes ( murders ) commited by young children .", 
        "obfuscation-id": 24, 
        "original": " \nIn America this question has been raised after a couple of serious crimes (murders) commited by young children.", 
        "original-end-charpos": 1933, 
        "original-start-charpos": 1821
    }, 
    {
        "obfuscation": "The blame is much laid on violent and bloody movies and video games , but is it really that easy ?", 
        "obfuscation-id": 25, 
        "original": " \nThe blame is often laid on violent and bloody movies and video games, but is it really that easy?", 
        "original-end-charpos": 2032, 
        "original-start-charpos": 1934
    }, 
    {
        "obfuscation": "It is not correct to assume that kids can distinguish between the real world and the world of TV and video games without someone to guide them .", 
        "obfuscation-id": 26, 
        "original": " \nIt is not right to assume that kids can distinguish between the real world and the world of TV and video games without someone to guide them.", 
        "original-end-charpos": 2175, 
        "original-start-charpos": 2033
    }, 
    {
        "obfuscation": "We have to remember that even if we are humans we are still animals as well .", 
        "obfuscation-id": 27, 
        "original": " \nWe have to remember that even if we are humans we are still animals as well.", 
        "original-end-charpos": 2253, 
        "original-start-charpos": 2176
    }, 
    {
        "obfuscation": "Just like other mammals our kids learn how to act by determining and mimicing grown-ups .", 
        "obfuscation-id": 28, 
        "original": " \nJust like other mammals our kids learn how to act by watching and mimicing grown-ups.", 
        "original-end-charpos": 2340, 
        "original-start-charpos": 2254
    }, 
    {
        "obfuscation": "There are other problems alongside the violence .", 
        "obfuscation-id": 29, 
        "original": " \nThere are other problems alongside the violence.", 
        "original-end-charpos": 2390, 
        "original-start-charpos": 2341
    }, 
    {
        "obfuscation": "TV very much has a narrow perspective of people 's looks .", 
        "obfuscation-id": 30, 
        "original": " \nTV very often has a narrow perspective of people's looks.", 
        "original-end-charpos": 2449, 
        "original-start-charpos": 2391
    }, 
    {
        "obfuscation": "On MTV , in soap operas and many other shows young people watch , the only way to look as a girl is to be thin , preferably with large breasts .", 
        "obfuscation-id": 31, 
        "original": " \nOn MTV, in soap operas and many other shows young people watch, the only way to look as a girl is to be thin, preferably with big breasts.", 
        "original-end-charpos": 2589, 
        "original-start-charpos": 2450
    }, 
    {
        "obfuscation": "For men it is significant to be tall and muscular .", 
        "obfuscation-id": 32, 
        "original": " \nFor men it is important to be tall and muscular.", 
        "original-end-charpos": 2639, 
        "original-start-charpos": 2590
    }, 
    {
        "obfuscation": "As a result girls , not yet teenagers , desire to operate their breasts , while boys are caught eating steroides .", 
        "obfuscation-id": 33, 
        "original": " \nAs a result girls, not yet teenagers, want to operate their breasts, while boys are caught eating steroides.", 
        "original-end-charpos": 2749, 
        "original-start-charpos": 2640
    }, 
    {
        "obfuscation": "The responsibility for what kids watch on TV and how much they watch lies of course with the parents .", 
        "obfuscation-id": 34, 
        "original": "  \nThe responsibility for what kids watch on TV and how much they watch lies of course with the parents.", 
        "original-end-charpos": 2853, 
        "original-start-charpos": 2750
    }, 
    {
        "obfuscation": "To forbid the use of TV would n't really solve anything .", 
        "obfuscation-id": 35, 
        "original": " \nTo forbid the use of TV wouldn't really solve anything.", 
        "original-end-charpos": 2910, 
        "original-start-charpos": 2854
    }, 
    {
        "obfuscation": "One must not forget that TV is our large source of information .", 
        "obfuscation-id": 36, 
        "original": " \nOne must not forget that TV is our biggest source of information.", 
        "original-end-charpos": 2977, 
        "original-start-charpos": 2911
    }, 
    {
        "obfuscation": "That makes it an amazing tool for doing things you normally could not do .", 
        "obfuscation-id": 37, 
        "original": " \nThat makes it an amazing tool for doing things you normally could not do.", 
        "original-end-charpos": 3052, 
        "original-start-charpos": 2978
    }, 
    {
        "obfuscation": "Via the TV one can travel all over the world , meet all kinds of unlike cultures , learn languages , take trips thru time both to the past and the future and much more .", 
        "obfuscation-id": 38, 
        "original": " \nVia the TV one can travel all over the world, meet all kinds of different cultures, learn languages, take trips thru time both to the past and the future and much more.", 
        "original-end-charpos": 3222, 
        "original-start-charpos": 3053
    }, 
    {
        "obfuscation": "When treated right it is a valuable tool in school as well as home .", 
        "obfuscation-id": 39, 
        "original": " \nWhen treated right it is a valuable tool in school as well as home.", 
        "original-end-charpos": 3291, 
        "original-start-charpos": 3223
    }, 
    {
        "obfuscation": "The problem is that our society today demands a lot from people .", 
        "obfuscation-id": 40, 
        "original": " \nThe problem is that our society today demands a lot from people.", 
        "original-end-charpos": 3357, 
        "original-start-charpos": 3292
    }, 
    {
        "obfuscation": "Everyone is supposed to make eveything everyone else does .", 
        "obfuscation-id": 41, 
        "original": " \nEveryone is supposed to do eveything everyone else does.", 
        "original-end-charpos": 3415, 
        "original-start-charpos": 3358
    }, 
    {
        "obfuscation": "There is no wonder kids are forgotten , since they seldom complain .", 
        "obfuscation-id": 42, 
        "original": " \nThere is no wonder kids are forgotten, since they seldom complain.", 
        "original-end-charpos": 3483, 
        "original-start-charpos": 3416
    }, 
    {
        "obfuscation": "If parents ( and other grown-ups as well ) take their duty and take better care for what children watch on TV and maybe even join them and explain things , the world might look different .", 
        "obfuscation-id": 43, 
        "original": " \nIf parents (and other grown-ups as well) take their responsibility and take better care for what children watch on TV and maybe even join them and explain things, the world might look different.", 
        "original-end-charpos": 3679, 
        "original-start-charpos": 3484
    }, 
    {
        "obfuscation": "It is worth a try because like it or not , we 're stuck with TV .", 
        "obfuscation-id": 44, 
        "original": " \nIt is worth a try because like it or not, we're stuck with TV.\n", 
        "original-end-charpos": 3744, 
        "original-start-charpos": 3680
    }
]